Workbook
Name 元請リスト: 元請マスタ!$A$2:$A$121
Name 現場リスト: 地名マスタ!$A$2:$A$201
Name 車番リスト: 車両マスタ!$A$2:$A$101
Name 運転手リスト: 運転手マスタ!$A$2:$A$101
Name 傭車リスト: 傭車マスタ!$A$2:$A$101
Name 区分リスト: 裏集計!$A$2:$A$4
Name 傭車区分リスト: 裏集計!$B$2:$B$3
Name チェックリスト: 裏集計!$C$2:$C$3

Sheet メイン
B2: トラック配車システム
B4: 使いたい画面の大きなボタンをクリックしてください
B6: 配車入力 | H6: 請求用配車
B12: 明日の配車を組む(毎日の入力はここから) | H12: 実績を整理する(請求書のもと)
B15: 自社売上票 | H15: 単価表
B21: 自社車両の日別売上を管理する | H21: 会社ごとの単価(昼/夜/その他)を管理する
B24: 請求書 | H24: 印刷
B30: 請求書を作成する | H30: 配車表を印刷する
B33: ※マスタ(車両・運転手・元請・地名・傭車・単価)や旧配車表・裏集計は非表示シートに保管されています。通常操作では触る必要はありません。

Sheet 配車入力
A1: 配車入力(前日配車表) | I1: ◀ メインへ戻る
A2: 黄色いセルに入力してください。前日にその日の配車を組むための表です。 | K2: その日出勤している運転手を○/×でチェックできます(運転手マスタと連動)。
K3: 出勤チェック(対象日)
A4: 日付 | B4: 元請 | C4: 現場名 | D4: 台数 | E4: 自社車番 | F4: 傭車 | G4: 傭車名 | H4: 備考 | K4: 運転手名 | L4: 出勤
K5: =IF(運転手マスタ!A2="","",運転手マスタ!A2)
K6: =IF(運転手マスタ!A3="","",運転手マスタ!A3)
K7: =IF(運転手マスタ!A4="","",運転手マスタ!A4)
K8: =IF(運転手マスタ!A5="","",運転手マスタ!A5)
K9: =IF(運転手マスタ!A6="","",運転手マスタ!A6)
K10: =IF(運転手マスタ!A7="","",運転手マスタ!A7)
K11: =IF(運転手マスタ!A8="","",運転手マスタ!A8)
K12: =IF(運転手マスタ!A9="","",運転手マスタ!A9)
K13: =IF(運転手マスタ!A10="","",運転手マスタ!A10)
K14: =IF(運転手マスタ!A11="","",運転手マスタ!A11)
K15: =IF(運転手マスタ!A12="","",運転手マスタ!A12)
K16: =IF(運転手マスタ!A13="","",運転手マスタ!A13)
... K22: =IF(運転手マスタ!A19="","",運転手マスタ!A19)

Sheet 請求用配車
A1: 請求用配車(実績整理) | N1: ◀ メインへ戻る
A2: 『配車入力』を見ながら、実際にあった内容をこの表に書き写してください(自動転記はしません)。単価は『単価表』を見て入力してください。金額は数量H×単価で自動計算されます。4t車の場合は元請欄に「会社名 4t車」と入力してください。
A4: 日付 | B4: 元請 | C4: 現場名 | D4: 台数 | E4: 自社車番 | F4: 運転手 | G4: 傭車名 | H4: 区分(昼/夜/その他) | I4: 数量H | J4: 単価 | K4: 金額 | L4: チェック | M4: 備考
K5: =IF(AND($I5<>"",$J5<>""),$I5*$J5,"")
K6: =IF(AND($I6<>"",$J6<>""),$I6*$J6,"")
K7: =IF(AND($I7<>"",$J7<>""),$I7*$J7,"")
K8: =IF(AND($I8<>"",$J8<>""),$I8*$J8,"")
K9: =IF(AND($I9<>"",$J9<>""),$I9*$J9,"")
K10: =IF(AND($I10<>"",$J10<>""),$I10*$J10,"")
K11: =IF(AND($I11<>"",$J11<>""),$I11*$J11,"")
K12: =IF(AND($I12<>"",$J12<>""),$I12*$J12,"")
K13: =IF(AND($I13<>"",$J13<>""),$I13*$J13,"")
K14: =IF(AND($I14<>"",$J14<>""),$I14*$J14,"")
K15: =IF(AND($I15<>"",$J15<>""),$I15*$J15,"")
K16: =IF(AND($I16<>"",$J16<>""),$I16*$J16,"")
... K204: =IF(AND($I204<>"",$J204<>""),$I204*$J204,"")

Sheet 自社売上票
A1: 自社売上票 | AI1: ◀ メインへ戻る
A3: 対象月 | D3: 日別売上欄には金額を入力してください。休みの日は「休」と入力すると月合計・日数の計算から自動で除外されます。
A5: 運転手名 | B5: 車検日 | C5: 車番 | D5: 1 | E5: 2 | F5: 3 | G5: 4 | H5: 5 | I5: 6 | J5: 7 | K5: 8 | L5: 9 | M5: 10 | N5: 11 | O5: 12 | P5: 13 | Q5: 14 | R5: 15 | S5: 16 | T5: 17 | U5: 18 | V5: 19 | W5: 20 | X5: 21 | Y5: 22 | Z5: 23 | AA5: 24 | AB5: 25 | AC5: 26 | AD5: 27 | AE5: 28 | AF5: 29 | AG5: 30 | AH5: 31 | AI5: 休 | AJ5: 月合計 | AK5: 日数 | AL5: 1日平均
AI6: =COUNTIF(D6:AH6,"休") | AJ6: =SUM(D6:AH6) | AK6: =COUNT(D6:AH6) | AL6: =IFERROR(AJ6/AK6,0)
AI7: =COUNTIF(D7:AH7,"休") | AJ7: =SUM(D7:AH7) | AK7: =COUNT(D7:AH7) | AL7: =IFERROR(AJ7/AK7,0)
AI8: =COUNTIF(D8:AH8,"休") | AJ8: =SUM(D8:AH8) | AK8: =COUNT(D8:AH8) | AL8: =IFERROR(AJ8/AK8,0)
AI9: =COUNTIF(D9:AH9,"休") | AJ9: =SUM(D9:AH9) | AK9: =COUNT(D9:AH9) | AL9: =IFERROR(AJ9/AK9,0)
AI10: =COUNTIF(D10:AH10,"休") | AJ10: =SUM(D10:AH10) | AK10: =COUNT(D10:AH10) | AL10: =IFERROR(AJ10/AK10,0)
AI11: =COUNTIF(D11:AH11,"休") | AJ11: =SUM(D11:AH11) | AK11: =COUNT(D11:AH11) | AL11: =IFERROR(AJ11/AK11,0)
AI12: =COUNTIF(D12:AH12,"休") | AJ12: =SUM(D12:AH12) | AK12: =COUNT(D12:AH12) | AL12: =IFERROR(AJ12/AK12,0)
AI13: =COUNTIF(D13:AH13,"休") | AJ13: =SUM(D13:AH13) | AK13: =COUNT(D13:AH13) | AL13: =IFERROR(AJ13/AK13,0)
AI14: =COUNTIF(D14:AH14,"休") | AJ14: =SUM(D14:AH14) | AK14: =COUNT(D14:AH14) | AL14: =IFERROR(AJ14/AK14,0)
AI15: =COUNTIF(D15:AH15,"休") | AJ15: =SUM(D15:AH15) | AK15: =COUNT(D15:AH15) | AL15: =IFERROR(AJ15/AK15,0)
AI16: =COUNTIF(D16:AH16,"休") | AJ16: =SUM(D16:AH16) | AK16: =COUNT(D16:AH16) | AL16: =IFERROR(AJ16/AK16,0)
AI17: =COUNTIF(D17:AH17,"休") | AJ17: =SUM(D17:AH17) | AK17: =COUNT(D17:AH17) | AL17: =IFERROR(AJ17/AK17,0)
... AI25: =COUNTIF(D25:AH25,"休") | AJ25: =SUM(D25:AH25) | AK25: =COUNT(D25:AH25) | AL25: =IFERROR(AJ25/AK25,0)

Sheet 単価表
A1: 単価表 | H1: ◀ メインへ戻る
A2: 会社ごとに 昼/夜/その他 の単価を管理します。4t車は別行として「会社名 4t車」のように登録してください(既存の単価表の運用にあわせています)。適用開始日を分ければ単価改定にも対応できます。
A3: 既存の単価表(2026/4/17時点)から実在86社を自動転記しました。日付・電話番号等のメモが混在していた価格欄はそのまま文字列で転記しているため、数値に直す場合はセルを直接編集してください。
A4: 会社名 | B4: 昼 | C4: 夜 | D4: その他 | E4: 適用開始日 | F4: 備考
A5: RK・KAWATA | B5: 36000
A6: ㈱俵口建設 | C6: 38000
A7: ㈱青木商店 | B7: 34000
A8: ㈱俵口建設 4t車 | B8: 24000
A9: ㈱淺沼組 | B9: 4/2 40,000
A10: ㈱フェアロード | B10: 4/1 40,000 | C10: 4/1 45,000
A11: ㈱一伸 | B11: 36000
A12: ㈱フェアロード 4t車 | B12: 4/1 30,000 | C12: 7/16 32,000
A13: 板橋産業
A14: ㈱福岡重機センター | B14: 6/3 40,000 | C14: 42000 | D14: 6/3 45,000
A15: ㈱イワシタ舗道 | B15: 34000 | C15: 42000
A16: 福山総合建設㈱ | B16: 40000 | C16: 4/1 37,000
A17: 永順産業㈱ | B17: 35000 | D17: (東部)38,000
A18: 藤木建設㈱ | B18: 40000 | C18: 2/15 38,000 | D18: 国交省 38,000
A19: ㈱エトウ | B19: 32000
A20: ㈱フジタ建設 | B20: 4/1 34,000
A21: ㈱大島組 | B21: 32000
A22: 藤田農園 | B22: 36000
A23: ㈱大森工業 | B23: 40000
A24: 増田運送㈲
A25: ㈱大山組 | B25: 36000
A26: ㈲松尾建設工業 | B26: 34000
A27: ㈱小田組 | B27: 34000
A28: ㈱松原土木 | B28: 34000
A29: カイダ建設㈱ | B29: 37000
A30: ㈲松本技建 | B30: 35000
A31: 金子建設興業㈲ | B31: 34000
A32: 宮﨑・ヤナギJV | B32: 33000
A33: 川越建設㈱ | B33: 40000 | C33: 45000
A34: ㈱松尾組 | B34: 38000
A35: 木内産業運輸㈱ | B35: 32000
A36: ㈱松尾道路 | B36: 38000
A37: ㈲北九州環境サポート | B37: 40000
A38: ㈱宮﨑組 | B38: TEL 37000
A39: 協和建設㈱ | B39: 4/2 40,000
A40: ㈱宮本組 | B40: 4/2 40,000
A41: ㈲享和工業 | B41: 32000
A42: ㈱宮本舗道工業 | B42: 40000 | C42: 43000 | D42: 2/16 TEL社長
A43: ㈱久保建設 | B43: 36000 | C43: 42000
A44: ㈱八幡道路 | B44: 40000 | C44: 45000
A45: 晃永工業㈲ | B45: 40000
A46: ㈱山賀 | B46: 40000
A47: 晃永工業㈲ 4t車 | B47: 26000
A48: ㈱山住工業 | B48: 34000
A49: ㈱高信産業 | B49: 40000
A50: ㈱山瀬組 | B50: 34000
A51: 興和道路㈱ | B51: 40000 | C51: 45000
A52: ㈲山田建設興業 | B52: 34000
A53: 興和道路㈱ 4t車 | B53: 26000 | C53: 29000 | D53: 昼 11/18TEL
A54: ㈲山田建設興業 ﾌｪｱﾛｰﾄﾞ | B54: 33000 | C54: 36000
A55: 小西建設興業㈱ | B55: 40000 | D55: Lｹﾞｰﾄ 42,000
A56: ㈲山田建設興業 4t車 | B56: 26000
A57: 小林建設㈱ | B57: 40000 | C57: 4/23 38,000 | D57: Lｹﾞｰﾄ 40,000
A58: ㈱友和建設 | B58: 40000
A59: 坂口組 | B59: 20000
A60: ㈱友和建設 4t車 | B60: 24000
A61: 三共建設㈱合材工場
A62: ㈲ヨシアキ建設 | B62: 40000
A63: ㈲三建建設 | B63: 40000
A64: ローカルワーカー㈱ | B64: 36000
A65: ㈱塩月工業 | B65: 36000
A66: 浅沼・有田JV | B66: 5/12 38,000
A67: ㈱スズキ | B67: 40000 | C67: 45000
A68: 鹿島道路㈱ | B68: 39000
A69: ㈱大新 | B69: 5/8 38,000
A70: YAMAZAKI | B70: 40000
A71: 大成ロテック㈱ | B71: 38000
A72: ㈱山口舗道 | B72: 4/3 40,000
A73: ㈱高瀬組 | B73: 35000 | C73: 興和(夜)39,000
A74: 竹本産業㈲ | B74: 32000
A75: ㈲東洋開発 | B75: 40000 | C75: 45000
A76: ㈱東陽建工 | B76: 34000
A77: ㈲永井運輸 | B77: 34000 | C77: 34000
A78: ㈱永津建設 | B78: 35000
A79: 中村建設 | B79: 34000 | C79: 38000 | D79: 国交省 34,000
A80: 中村工業㈱ | B80: 40000
A81: 中本重機㈱ | B81: 34000 | C81: 38000
A82: ㈱西村砕石大谷工場 | B82: 35000
A83: ㈲西村組 | B83: 38000
A84: 日本道路㈱福岡合材センター | B84: 40000 | C84: 45000
A85: 日本道路㈱福岡合材センター 4t車 | B85: 30000
A86: ㈱日本物流サービス | B86: 34000
A87: 梅光産業㈱
A88: ㈱早川建設 | B88: 40000
A89: ㈱PIT | B89: 35000
A90: ㈱PIT 4t車 | B90: 25000

Sheet 請求書
A1: 請求書 | G1: ◀ メインへ戻る
A3: 請求先 | D3: 税込合計金額 | E3: =ROUND(SUM(F9:F68)*1.1,0)
A4: 請求日 | D4: 消費税10% | E4: =ROUND(SUM(F9:F68)*0.1,0)
A6: 『請求用配車』のチェック済みの行を見ながら、この表に書き写してください。同じ名称が続く場合は紙と同じく「〃」と入力してください。
A7: 金額(F列)だけは数量×単価で自動計算されます。それ以外は手入力です。
A8: 日付 | B8: 名称 | C8: 台数 | D8: 数量 | E8: 単価 | F8: 金額 | G8: 車番 | H8: 備考
F9: =IF(AND($D9<>"",$E9<>""),$D9*$E9,"")
F10: =IF(AND($D10<>"",$E10<>""),$D10*$E10,"")
F11: =IF(AND($D11<>"",$E11<>""),$D11*$E11,"")
F12: =IF(AND($D12<>"",$E12<>""),$D12*$E12,"")
F13: =IF(AND($D13<>"",$E13<>""),$D13*$E13,"")
F14: =IF(AND($D14<>"",$E14<>""),$D14*$E14,"")
F15: =IF(AND($D15<>"",$E15<>""),$D15*$E15,"")
F16: =IF(AND($D16<>"",$E16<>""),$D16*$E16,"")
F17: =IF(AND($D17<>"",$E17<>""),$D17*$E17,"")
F18: =IF(AND($D18<>"",$E18<>""),$D18*$E18,"")
F19: =IF(AND($D19<>"",$E19<>""),$D19*$E19,"")
F20: =IF(AND($D20<>"",$E20<>""),$D20*$E20,"")
... F68: =IF(AND($D68<>"",$E68<>""),$D68*$E68,"")

Sheet 印刷
A1: 配車表(印刷用) | I1: ◀ メインへ戻る
A2: 『配車入力』の内容がそのまま反映されます。オートフィルタで日付を絞り込んでから印刷してください(Ctrl+P)。
A4: 日付 | B4: 元請 | C4: 現場名 | D4: 台数 | E4: 自社車番 | F4: 傭車 | G4: 傭車名 | H4: 備考
A5: =IF('配車入力'!A5="","",'配車入力'!A5) | B5: =IF('配車入力'!B5="","",'配車入力'!B5) | C5: =IF('配車入力'!C5="","",'配車入力'!C5) | D5: =IF('配車入力'!D5="","",'配車入力'!D5) | E5: =IF('配車入力'!E5="","",'配車入力'!E5) | F5: =IF('配車入力'!F5="","",'配車入力'!F5) | G5: =IF('配車入力'!G5="","",'配車入力'!G5) | H5: =IF('配車入力'!H5="","",'配車入力'!H5)
A6: =IF('配車入力'!A6="","",'配車入力'!A6) | B6: =IF('配車入力'!B6="","",'配車入力'!B6) | C6: =IF('配車入力'!C6="","",'配車入力'!C6) | D6: =IF('配車入力'!D6="","",'配車入力'!D6) | E6: =IF('配車入力'!E6="","",'配車入力'!E6) | F6: =IF('配車入力'!F6="","",'配車入力'!F6) | G6: =IF('配車入力'!G6="","",'配車入力'!G6) | H6: =IF('配車入力'!H6="","",'配車入力'!H6)
A7: =IF('配車入力'!A7="","",'配車入力'!A7) | B7: =IF('配車入力'!B7="","",'配車入力'!B7) | C7: =IF('配車入力'!C7="","",'配車入力'!C7) | D7: =IF('配車入力'!D7="","",'配車入力'!D7) | E7: =IF('配車入力'!E7="","",'配車入力'!E7) | F7: =IF('配車入力'!F7="","",'配車入力'!F7) | G7: =IF('配車入力'!G7="","",'配車入力'!G7) | H7: =IF('配車入力'!H7="","",'配車入力'!H7)
A8: =IF('配車入力'!A8="","",'配車入力'!A8) | B8: =IF('配車入力'!B8="","",'配車入力'!B8) | C8: =IF('配車入力'!C8="","",'配車入力'!C8) | D8: =IF('配車入力'!D8="","",'配車入力'!D8) | E8: =IF('配車入力'!E8="","",'配車入力'!E8) | F8: =IF('配車入力'!F8="","",'配車入力'!F8) | G8: =IF('配車入力'!G8="","",'配車入力'!G8) | H8: =IF('配車入力'!H8="","",'配車入力'!H8)
A9: =IF('配車入力'!A9="","",'配車入力'!A9) | B9: =IF('配車入力'!B9="","",'配車入力'!B9) | C9: =IF('配車入力'!C9="","",'配車入力'!C9) | D9: =IF('配車入力'!D9="","",'配車入力'!D9) | E9: =IF('配車入力'!E9="","",'配車入力'!E9) | F9: =IF('配車入力'!F9="","",'配車入力'!F9) | G9: =IF('配車入力'!G9="","",'配車入力'!G9) | H9: =IF('配車入力'!H9="","",'配車入力'!H9)
A10: =IF('配車入力'!A10="","",'配車入力'!A10) | B10: =IF('配車入力'!B10="","",'配車入力'!B10) | C10: =IF('配車入力'!C10="","",'配車入力'!C10) | D10: =IF('配車入力'!D10="","",'配車入力'!D10) | E10: =IF('配車入力'!E10="","",'配車入力'!E10) | F10: =IF('配車入力'!F10="","",'配車入力'!F10) | G10: =IF('配車入力'!G10="","",'配車入力'!G10) | H10: =IF('配車入力'!H10="","",'配車入力'!H10)
A11: =IF('配車入力'!A11="","",'配車入力'!A11) | B11: =IF('配車入力'!B11="","",'配車入力'!B11) | C11: =IF('配車入力'!C11="","",'配車入力'!C11) | D11: =IF('配車入力'!D11="","",'配車入力'!D11) | E11: =IF('配車入力'!E11="","",'配車入力'!E11) | F11: =IF('配車入力'!F11="","",'配車入力'!F11) | G11: =IF('配車入力'!G11="","",'配車入力'!G11) | H11: =IF('配車入力'!H11="","",'配車入力'!H11)
A12: =IF('配車入力'!A12="","",'配車入力'!A12) | B12: =IF('配車入力'!B12="","",'配車入力'!B12) | C12: =IF('配車入力'!C12="","",'配車入力'!C12) | D12: =IF('配車入力'!D12="","",'配車入力'!D12) | E12: =IF('配車入力'!E12="","",'配車入力'!E12) | F12: =IF('配車入力'!F12="","",'配車入力'!F12) | G12: =IF('配車入力'!G12="","",'配車入力'!G12) | H12: =IF('配車入力'!H12="","",'配車入力'!H12)
A13: =IF('配車入力'!A13="","",'配車入力'!A13) | B13: =IF('配車入力'!B13="","",'配車入力'!B13) | C13: =IF('配車入力'!C13="","",'配車入力'!C13) | D13: =IF('配車入力'!D13="","",'配車入力'!D13) | E13: =IF('配車入力'!E13="","",'配車入力'!E13) | F13: =IF('配車入力'!F13="","",'配車入力'!F13) | G13: =IF('配車入力'!G13="","",'配車入力'!G13) | H13: =IF('配車入力'!H13="","",'配車入力'!H13)
A14: =IF('配車入力'!A14="","",'配車入力'!A14) | B14: =IF('配車入力'!B14="","",'配車入力'!B14) | C14: =IF('配車入力'!C14="","",'配車入力'!C14) | D14: =IF('配車入力'!D14="","",'配車入力'!D14) | E14: =IF('配車入力'!E14="","",'配車入力'!E14) | F14: =IF('配車入力'!F14="","",'配車入力'!F14) | G14: =IF('配車入力'!G14="","",'配車入力'!G14) | H14: =IF('配車入力'!H14="","",'配車入力'!H14)
A15: =IF('配車入力'!A15="","",'配車入力'!A15) | B15: =IF('配車入力'!B15="","",'配車入力'!B15) | C15: =IF('配車入力'!C15="","",'配車入力'!C15) | D15: =IF('配車入力'!D15="","",'配車入力'!D15) | E15: =IF('配車入力'!E15="","",'配車入力'!E15) | F15: =IF('配車入力'!F15="","",'配車入力'!F15) | G15: =IF('配車入力'!G15="","",'配車入力'!G15) | H15: =IF('配車入力'!H15="","",'配車入力'!H15)
A16: =IF('配車入力'!A16="","",'配車入力'!A16) | B16: =IF('配車入力'!B16="","",'配車入力'!B16) | C16: =IF('配車入力'!C16="","",'配車入力'!C16) | D16: =IF('配車入力'!D16="","",'配車入力'!D16) | E16: =IF('配車入力'!E16="","",'配車入力'!E16) | F16: =IF('配車入力'!F16="","",'配車入力'!F16) | G16: =IF('配車入力'!G16="","",'配車入力'!G16) | H16: =IF('配車入力'!H16="","",'配車入力'!H16)
... A204: =IF('配車入力'!A204="","",'配車入力'!A204) | B204: =IF('配車入力'!B204="","",'配車入力'!B204) | C204: =IF('配車入力'!C204="","",'配車入力'!C204) | D204: =IF('配車入力'!D204="","",'配車入力'!D204) | E204: =IF('配車入力'!E204="","",'配車入力'!E204) | F204: =IF('配車入力'!F204="","",'配車入力'!F204) | G204: =IF('配車入力'!G204="","",'配車入力'!G204) | H204: =IF('配車入力'!H204="","",'配車入力'!H204)

Sheet 車両マスタ
A1: 自社車番 | B1: 車種 | C1: 既定運転手 | D1: 車検日

Sheet 運転手マスタ
A1: 運転手名 | B1: 電話番号 | C1: 備考
A2: 坂本
A3: 松興
A4: 興栄
A5: 山田
A6: 竹本
A7: 中村
A8: 金子
A9: フジタ
A10: 永井
A11: 久富
A12: 水谷
A13: 渡辺
... A19: 西本

Sheet 元請マスタ
A1: 元請名 | B1: 備考
A2: RK・KAWATA
A3: ㈱俵口建設
A4: ㈱青木商店
A5: ㈱俵口建設 4t車
A6: ㈱淺沼組
A7: ㈱フェアロード
A8: ㈱一伸
A9: ㈱フェアロード 4t車
A10: 板橋産業
A11: ㈱福岡重機センター
A12: ㈱イワシタ舗道
A13: 福山総合建設㈱
... A87: ㈱PIT 4t車

Sheet 地名マスタ
A1: 現場名 | B1: 関連元請 | C1: 備考

Sheet 傭車マスタ
A1: 傭車会社名 | B1: 連絡先 | C1: 備考

Sheet 単価マスタ
A1: 会社名 | B1: 区分 | C1: 単価 | D1: 適用開始日 | F1: ※単価表シートの内容を自動展開した一覧です。直接編集しないでください。
A2: =IF('単価表'!$A$5="","",'単価表'!$A$5) | B2: 昼 | C2: =IF('単価表'!$B$5="","",'単価表'!$B$5) | D2: =IF('単価表'!$E$5="","",'単価表'!$E$5)
A3: =IF('単価表'!$A$5="","",'単価表'!$A$5) | B3: 夜 | C3: =IF('単価表'!$C$5="","",'単価表'!$C$5) | D3: =IF('単価表'!$E$5="","",'単価表'!$E$5)
A4: =IF('単価表'!$A$5="","",'単価表'!$A$5) | B4: その他 | C4: =IF('単価表'!$D$5="","",'単価表'!$D$5) | D4: =IF('単価表'!$E$5="","",'単価表'!$E$5)
A5: =IF('単価表'!$A$6="","",'単価表'!$A$6) | B5: 昼 | C5: =IF('単価表'!$B$6="","",'単価表'!$B$6) | D5: =IF('単価表'!$E$6="","",'単価表'!$E$6)
A6: =IF('単価表'!$A$6="","",'単価表'!$A$6) | B6: 夜 | C6: =IF('単価表'!$C$6="","",'単価表'!$C$6) | D6: =IF('単価表'!$E$6="","",'単価表'!$E$6)
A7: =IF('単価表'!$A$6="","",'単価表'!$A$6) | B7: その他 | C7: =IF('単価表'!$D$6="","",'単価表'!$D$6) | D7: =IF('単価表'!$E$6="","",'単価表'!$E$6)
A8: =IF('単価表'!$A$7="","",'単価表'!$A$7) | B8: 昼 | C8: =IF('単価表'!$B$7="","",'単価表'!$B$7) | D8: =IF('単価表'!$E$7="","",'単価表'!$E$7)
A9: =IF('単価表'!$A$7="","",'単価表'!$A$7) | B9: 夜 | C9: =IF('単価表'!$C$7="","",'単価表'!$C$7) | D9: =IF('単価表'!$E$7="","",'単価表'!$E$7)
A10: =IF('単価表'!$A$7="","",'単価表'!$A$7) | B10: その他 | C10: =IF('単価表'!$D$7="","",'単価表'!$D$7) | D10: =IF('単価表'!$E$7="","",'単価表'!$E$7)
A11: =IF('単価表'!$A$8="","",'単価表'!$A$8) | B11: 昼 | C11: =IF('単価表'!$B$8="","",'単価表'!$B$8) | D11: =IF('単価表'!$E$8="","",'単価表'!$E$8)
A12: =IF('単価表'!$A$8="","",'単価表'!$A$8) | B12: 夜 | C12: =IF('単価表'!$C$8="","",'単価表'!$C$8) | D12: =IF('単価表'!$E$8="","",'単価表'!$E$8)
A13: =IF('単価表'!$A$8="","",'単価表'!$A$8) | B13: その他 | C13: =IF('単価表'!$D$8="","",'単価表'!$D$8) | D13: =IF('単価表'!$E$8="","",'単価表'!$E$8)
A14: =IF('単価表'!$A$9="","",'単価表'!$A$9) | B14: 昼 | C14: =IF('単価表'!$B$9="","",'単価表'!$B$9) | D14: =IF('単価表'!$E$9="","",'単価表'!$E$9)
A15: =IF('単価表'!$A$9="","",'単価表'!$A$9) | B15: 夜 | C15: =IF('単価表'!$C$9="","",'単価表'!$C$9) | D15: =IF('単価表'!$E$9="","",'単価表'!$E$9)
A16: =IF('単価表'!$A$9="","",'単価表'!$A$9) | B16: その他 | C16: =IF('単価表'!$D$9="","",'単価表'!$D$9) | D16: =IF('単価表'!$E$9="","",'単価表'!$E$9)
A17: =IF('単価表'!$A$10="","",'単価表'!$A$10) | B17: 昼 | C17: =IF('単価表'!$B$10="","",'単価表'!$B$10) | D17: =IF('単価表'!$E$10="","",'単価表'!$E$10)
A18: =IF('単価表'!$A$10="","",'単価表'!$A$10) | B18: 夜 | C18: =IF('単価表'!$C$10="","",'単価表'!$C$10) | D18: =IF('単価表'!$E$10="","",'単価表'!$E$10)
A19: =IF('単価表'!$A$10="","",'単価表'!$A$10) | B19: その他 | C19: =IF('単価表'!$D$10="","",'単価表'!$D$10) | D19: =IF('単価表'!$E$10="","",'単価表'!$E$10)
A20: =IF('単価表'!$A$11="","",'単価表'!$A$11) | B20: 昼 | C20: =IF('単価表'!$B$11="","",'単価表'!$B$11) | D20: =IF('単価表'!$E$11="","",'単価表'!$E$11)
A21: =IF('単価表'!$A$11="","",'単価表'!$A$11) | B21: 夜 | C21: =IF('単価表'!$C$11="","",'単価表'!$C$11) | D21: =IF('単価表'!$E$11="","",'単価表'!$E$11)
A22: =IF('単価表'!$A$11="","",'単価表'!$A$11) | B22: その他 | C22: =IF('単価表'!$D$11="","",'単価表'!$D$11) | D22: =IF('単価表'!$E$11="","",'単価表'!$E$11)
A23: =IF('単価表'!$A$12="","",'単価表'!$A$12) | B23: 昼 | C23: =IF('単価表'!$B$12="","",'単価表'!$B$12) | D23: =IF('単価表'!$E$12="","",'単価表'!$E$12)
A24: =IF('単価表'!$A$12="","",'単価表'!$A$12) | B24: 夜 | C24: =IF('単価表'!$C$12="","",'単価表'!$C$12) | D24: =IF('単価表'!$E$12="","",'単価表'!$E$12)
A25: =IF('単価表'!$A$12="","",'単価表'!$A$12) | B25: その他 | C25: =IF('単価表'!$D$12="","",'単価表'!$D$12) | D25: =IF('単価表'!$E$12="","",'単価表'!$E$12)
A26: =IF('単価表'!$A$13="","",'単価表'!$A$13) | B26: 昼 | C26: =IF('単価表'!$B$13="","",'単価表'!$B$13) | D26: =IF('単価表'!$E$13="","",'単価表'!$E$13)
A27: =IF('単価表'!$A$13="","",'単価表'!$A$13) | B27: 夜 | C27: =IF('単価表'!$C$13="","",'単価表'!$C$13) | D27: =IF('単価表'!$E$13="","",'単価表'!$E$13)
A28: =IF('単価表'!$A$13="","",'単価表'!$A$13) | B28: その他 | C28: =IF('単価表'!$D$13="","",'単価表'!$D$13) | D28: =IF('単価表'!$E$13="","",'単価表'!$E$13)
A29: =IF('単価表'!$A$14="","",'単価表'!$A$14) | B29: 昼 | C29: =IF('単価表'!$B$14="","",'単価表'!$B$14) | D29: =IF('単価表'!$E$14="","",'単価表'!$E$14)
A30: =IF('単価表'!$A$14="","",'単価表'!$A$14) | B30: 夜 | C30: =IF('単価表'!$C$14="","",'単価表'!$C$14) | D30: =IF('単価表'!$E$14="","",'単価表'!$E$14)
A31: =IF('単価表'!$A$14="","",'単価表'!$A$14) | B31: その他 | C31: =IF('単価表'!$D$14="","",'単価表'!$D$14) | D31: =IF('単価表'!$E$14="","",'単価表'!$E$14)
A32: =IF('単価表'!$A$15="","",'単価表'!$A$15) | B32: 昼 | C32: =IF('単価表'!$B$15="","",'単価表'!$B$15) | D32: =IF('単価表'!$E$15="","",'単価表'!$E$15)
A33: =IF('単価表'!$A$15="","",'単価表'!$A$15) | B33: 夜 | C33: =IF('単価表'!$C$15="","",'単価表'!$C$15) | D33: =IF('単価表'!$E$15="","",'単価表'!$E$15)
A34: =IF('単価表'!$A$15="","",'単価表'!$A$15) | B34: その他 | C34: =IF('単価表'!$D$15="","",'単価表'!$D$15) | D34: =IF('単価表'!$E$15="","",'単価表'!$E$15)
A35: =IF('単価表'!$A$16="","",'単価表'!$A$16) | B35: 昼 | C35: =IF('単価表'!$B$16="","",'単価表'!$B$16) | D35: =IF('単価表'!$E$16="","",'単価表'!$E$16)
A36: =IF('単価表'!$A$16="","",'単価表'!$A$16) | B36: 夜 | C36: =IF('単価表'!$C$16="","",'単価表'!$C$16) | D36: =IF('単価表'!$E$16="","",'単価表'!$E$16)
A37: =IF('単価表'!$A$16="","",'単価表'!$A$16) | B37: その他 | C37: =IF('単価表'!$D$16="","",'単価表'!$D$16) | D37: =IF('単価表'!$E$16="","",'単価表'!$E$16)
A38: =IF('単価表'!$A$17="","",'単価表'!$A$17) | B38: 昼 | C38: =IF('単価表'!$B$17="","",'単価表'!$B$17) | D38: =IF('単価表'!$E$17="","",'単価表'!$E$17)
A39: =IF('単価表'!$A$17="","",'単価表'!$A$17) | B39: 夜 | C39: =IF('単価表'!$C$17="","",'単価表'!$C$17) | D39: =IF('単価表'!$E$17="","",'単価表'!$E$17)
A40: =IF('単価表'!$A$17="","",'単価表'!$A$17) | B40: その他 | C40: =IF('単価表'!$D$17="","",'単価表'!$D$17) | D40: =IF('単価表'!$E$17="","",'単価表'!$E$17)
A41: =IF('単価表'!$A$18="","",'単価表'!$A$18) | B41: 昼 | C41: =IF('単価表'!$B$18="","",'単価表'!$B$18) | D41: =IF('単価表'!$E$18="","",'単価表'!$E$18)
A42: =IF('単価表'!$A$18="","",'単価表'!$A$18) | B42: 夜 | C42: =IF('単価表'!$C$18="","",'単価表'!$C$18) | D42: =IF('単価表'!$E$18="","",'単価表'!$E$18)
A43: =IF('単価表'!$A$18="","",'単価表'!$A$18) | B43: その他 | C43: =IF('単価表'!$D$18="","",'単価表'!$D$18) | D43: =IF('単価表'!$E$18="","",'単価表'!$E$18)
A44: =IF('単価表'!$A$19="","",'単価表'!$A$19) | B44: 昼 | C44: =IF('単価表'!$B$19="","",'単価表'!$B$19) | D44: =IF('単価表'!$E$19="","",'単価表'!$E$19)
A45: =IF('単価表'!$A$19="","",'単価表'!$A$19) | B45: 夜 | C45: =IF('単価表'!$C$19="","",'単価表'!$C$19) | D45: =IF('単価表'!$E$19="","",'単価表'!$E$19)
A46: =IF('単価表'!$A$19="","",'単価表'!$A$19) | B46: その他 | C46: =IF('単価表'!$D$19="","",'単価表'!$D$19) | D46: =IF('単価表'!$E$19="","",'単価表'!$E$19)
A47: =IF('単価表'!$A$20="","",'単価表'!$A$20) | B47: 昼 | C47: =IF('単価表'!$B$20="","",'単価表'!$B$20) | D47: =IF('単価表'!$E$20="","",'単価表'!$E$20)
A48: =IF('単価表'!$A$20="","",'単価表'!$A$20) | B48: 夜 | C48: =IF('単価表'!$C$20="","",'単価表'!$C$20) | D48: =IF('単価表'!$E$20="","",'単価表'!$E$20)
A49: =IF('単価表'!$A$20="","",'単価表'!$A$20) | B49: その他 | C49: =IF('単価表'!$D$20="","",'単価表'!$D$20) | D49: =IF('単価表'!$E$20="","",'単価表'!$E$20)
A50: =IF('単価表'!$A$21="","",'単価表'!$A$21) | B50: 昼 | C50: =IF('単価表'!$B$21="","",'単価表'!$B$21) | D50: =IF('単価表'!$E$21="","",'単価表'!$E$21)
A51: =IF('単価表'!$A$21="","",'単価表'!$A$21) | B51: 夜 | C51: =IF('単価表'!$C$21="","",'単価表'!$C$21) | D51: =IF('単価表'!$E$21="","",'単価表'!$E$21)
A52: =IF('単価表'!$A$21="","",'単価表'!$A$21) | B52: その他 | C52: =IF('単価表'!$D$21="","",'単価表'!$D$21) | D52: =IF('単価表'!$E$21="","",'単価表'!$E$21)
A53: =IF('単価表'!$A$22="","",'単価表'!$A$22) | B53: 昼 | C53: =IF('単価表'!$B$22="","",'単価表'!$B$22) | D53: =IF('単価表'!$E$22="","",'単価表'!$E$22)
A54: =IF('単価表'!$A$22="","",'単価表'!$A$22) | B54: 夜 | C54: =IF('単価表'!$C$22="","",'単価表'!$C$22) | D54: =IF('単価表'!$E$22="","",'単価表'!$E$22)
A55: =IF('単価表'!$A$22="","",'単価表'!$A$22) | B55: その他 | C55: =IF('単価表'!$D$22="","",'単価表'!$D$22) | D55: =IF('単価表'!$E$22="","",'単価表'!$E$22)
A56: =IF('単価表'!$A$23="","",'単価表'!$A$23) | B56: 昼 | C56: =IF('単価表'!$B$23="","",'単価表'!$B$23) | D56: =IF('単価表'!$E$23="","",'単価表'!$E$23)
A57: =IF('単価表'!$A$23="","",'単価表'!$A$23) | B57: 夜 | C57: =IF('単価表'!$C$23="","",'単価表'!$C$23) | D57: =IF('単価表'!$E$23="","",'単価表'!$E$23)
A58: =IF('単価表'!$A$23="","",'単価表'!$A$23) | B58: その他 | C58: =IF('単価表'!$D$23="","",'単価表'!$D$23) | D58: =IF('単価表'!$E$23="","",'単価表'!$E$23)
A59: =IF('単価表'!$A$24="","",'単価表'!$A$24) | B59: 昼 | C59: =IF('単価表'!$B$24="","",'単価表'!$B$24) | D59: =IF('単価表'!$E$24="","",'単価表'!$E$24)
A60: =IF('単価表'!$A$24="","",'単価表'!$A$24) | B60: 夜 | C60: =IF('単価表'!$C$24="","",'単価表'!$C$24) | D60: =IF('単価表'!$E$24="","",'単価表'!$E$24)
A61: =IF('単価表'!$A$24="","",'単価表'!$A$24) | B61: その他 | C61: =IF('単価表'!$D$24="","",'単価表'!$D$24) | D61: =IF('単価表'!$E$24="","",'単価表'!$E$24)
A62: =IF('単価表'!$A$25="","",'単価表'!$A$25) | B62: 昼 | C62: =IF('単価表'!$B$25="","",'単価表'!$B$25) | D62: =IF('単価表'!$E$25="","",'単価表'!$E$25)
A63: =IF('単価表'!$A$25="","",'単価表'!$A$25) | B63: 夜 | C63: =IF('単価表'!$C$25="","",'単価表'!$C$25) | D63: =IF('単価表'!$E$25="","",'単価表'!$E$25)
A64: =IF('単価表'!$A$25="","",'単価表'!$A$25) | B64: その他 | C64: =IF('単価表'!$D$25="","",'単価表'!$D$25) | D64: =IF('単価表'!$E$25="","",'単価表'!$E$25)
A65: =IF('単価表'!$A$26="","",'単価表'!$A$26) | B65: 昼 | C65: =IF('単価表'!$B$26="","",'単価表'!$B$26) | D65: =IF('単価表'!$E$26="","",'単価表'!$E$26)
A66: =IF('単価表'!$A$26="","",'単価表'!$A$26) | B66: 夜 | C66: =IF('単価表'!$C$26="","",'単価表'!$C$26) | D66: =IF('単価表'!$E$26="","",'単価表'!$E$26)
A67: =IF('単価表'!$A$26="","",'単価表'!$A$26) | B67: その他 | C67: =IF('単価表'!$D$26="","",'単価表'!$D$26) | D67: =IF('単価表'!$E$26="","",'単価表'!$E$26)
A68: =IF('単価表'!$A$27="","",'単価表'!$A$27) | B68: 昼 | C68: =IF('単価表'!$B$27="","",'単価表'!$B$27) | D68: =IF('単価表'!$E$27="","",'単価表'!$E$27)
A69: =IF('単価表'!$A$27="","",'単価表'!$A$27) | B69: 夜 | C69: =IF('単価表'!$C$27="","",'単価表'!$C$27) | D69: =IF('単価表'!$E$27="","",'単価表'!$E$27)
A70: =IF('単価表'!$A$27="","",'単価表'!$A$27) | B70: その他 | C70: =IF('単価表'!$D$27="","",'単価表'!$D$27) | D70: =IF('単価表'!$E$27="","",'単価表'!$E$27)
A71: =IF('単価表'!$A$28="","",'単価表'!$A$28) | B71: 昼 | C71: =IF('単価表'!$B$28="","",'単価表'!$B$28) | D71: =IF('単価表'!$E$28="","",'単価表'!$E$28)
A72: =IF('単価表'!$A$28="","",'単価表'!$A$28) | B72: 夜 | C72: =IF('単価表'!$C$28="","",'単価表'!$C$28) | D72: =IF('単価表'!$E$28="","",'単価表'!$E$28)
A73: =IF('単価表'!$A$28="","",'単価表'!$A$28) | B73: その他 | C73: =IF('単価表'!$D$28="","",'単価表'!$D$28) | D73: =IF('単価表'!$E$28="","",'単価表'!$E$28)
A74: =IF('単価表'!$A$29="","",'単価表'!$A$29) | B74: 昼 | C74: =IF('単価表'!$B$29="","",'単価表'!$B$29) | D74: =IF('単価表'!$E$29="","",'単価表'!$E$29)
A75: =IF('単価表'!$A$29="","",'単価表'!$A$29) | B75: 夜 | C75: =IF('単価表'!$C$29="","",'単価表'!$C$29) | D75: =IF('単価表'!$E$29="","",'単価表'!$E$29)
A76: =IF('単価表'!$A$29="","",'単価表'!$A$29) | B76: その他 | C76: =IF('単価表'!$D$29="","",'単価表'!$D$29) | D76: =IF('単価表'!$E$29="","",'単価表'!$E$29)
A77: =IF('単価表'!$A$30="","",'単価表'!$A$30) | B77: 昼 | C77: =IF('単価表'!$B$30="","",'単価表'!$B$30) | D77: =IF('単価表'!$E$30="","",'単価表'!$E$30)
A78: =IF('単価表'!$A$30="","",'単価表'!$A$30) | B78: 夜 | C78: =IF('単価表'!$C$30="","",'単価表'!$C$30) | D78: =IF('単価表'!$E$30="","",'単価表'!$E$30)
A79: =IF('単価表'!$A$30="","",'単価表'!$A$30) | B79: その他 | C79: =IF('単価表'!$D$30="","",'単価表'!$D$30) | D79: =IF('単価表'!$E$30="","",'単価表'!$E$30)
A80: =IF('単価表'!$A$31="","",'単価表'!$A$31) | B80: 昼 | C80: =IF('単価表'!$B$31="","",'単価表'!$B$31) | D80: =IF('単価表'!$E$31="","",'単価表'!$E$31)
A81: =IF('単価表'!$A$31="","",'単価表'!$A$31) | B81: 夜 | C81: =IF('単価表'!$C$31="","",'単価表'!$C$31) | D81: =IF('単価表'!$E$31="","",'単価表'!$E$31)
A82: =IF('単価表'!$A$31="","",'単価表'!$A$31) | B82: その他 | C82: =IF('単価表'!$D$31="","",'単価表'!$D$31) | D82: =IF('単価表'!$E$31="","",'単価表'!$E$31)
A83: =IF('単価表'!$A$32="","",'単価表'!$A$32) | B83: 昼 | C83: =IF('単価表'!$B$32="","",'単価表'!$B$32) | D83: =IF('単価表'!$E$32="","",'単価表'!$E$32)
A84: =IF('単価表'!$A$32="","",'単価表'!$A$32) | B84: 夜 | C84: =IF('単価表'!$C$32="","",'単価表'!$C$32) | D84: =IF('単価表'!$E$32="","",'単価表'!$E$32)
A85: =IF('単価表'!$A$32="","",'単価表'!$A$32) | B85: その他 | C85: =IF('単価表'!$D$32="","",'単価表'!$D$32) | D85: =IF('単価表'!$E$32="","",'単価表'!$E$32)
A86: =IF('単価表'!$A$33="","",'単価表'!$A$33) | B86: 昼 | C86: =IF('単価表'!$B$33="","",'単価表'!$B$33) | D86: =IF('単価表'!$E$33="","",'単価表'!$E$33)
A87: =IF('単価表'!$A$33="","",'単価表'!$A$33) | B87: 夜 | C87: =IF('単価表'!$C$33="","",'単価表'!$C$33) | D87: =IF('単価表'!$E$33="","",'単価表'!$E$33)
A88: =IF('単価表'!$A$33="","",'単価表'!$A$33) | B88: その他 | C88: =IF('単価表'!$D$33="","",'単価表'!$D$33) | D88: =IF('単価表'!$E$33="","",'単価表'!$E$33)
A89: =IF('単価表'!$A$34="","",'単価表'!$A$34) | B89: 昼 | C89: =IF('単価表'!$B$34="","",'単価表'!$B$34) | D89: =IF('単価表'!$E$34="","",'単価表'!$E$34)
A90: =IF('単価表'!$A$34="","",'単価表'!$A$34) | B90: 夜 | C90: =IF('単価表'!$C$34="","",'単価表'!$C$34) | D90: =IF('単価表'!$E$34="","",'単価表'!$E$34)
A91: =IF('単価表'!$A$34="","",'単価表'!$A$34) | B91: その他 | C91: =IF('単価表'!$D$34="","",'単価表'!$D$34) | D91: =IF('単価表'!$E$34="","",'単価表'!$E$34)
A92: =IF('単価表'!$A$35="","",'単価表'!$A$35) | B92: 昼 | C92: =IF('単価表'!$B$35="","",'単価表'!$B$35) | D92: =IF('単価表'!$E$35="","",'単価表'!$E$35)
A93: =IF('単価表'!$A$35="","",'単価表'!$A$35) | B93: 夜 | C93: =IF('単価表'!$C$35="","",'単価表'!$C$35) | D93: =IF('単価表'!$E$35="","",'単価表'!$E$35)
A94: =IF('単価表'!$A$35="","",'単価表'!$A$35) | B94: その他 | C94: =IF('単価表'!$D$35="","",'単価表'!$D$35) | D94: =IF('単価表'!$E$35="","",'単価表'!$E$35)
A95: =IF('単価表'!$A$36="","",'単価表'!$A$36) | B95: 昼 | C95: =IF('単価表'!$B$36="","",'単価表'!$B$36) | D95: =IF('単価表'!$E$36="","",'単価表'!$E$36)
A96: =IF('単価表'!$A$36="","",'単価表'!$A$36) | B96: 夜 | C96: =IF('単価表'!$C$36="","",'単価表'!$C$36) | D96: =IF('単価表'!$E$36="","",'単価表'!$E$36)
A97: =IF('単価表'!$A$36="","",'単価表'!$A$36) | B97: その他 | C97: =IF('単価表'!$D$36="","",'単価表'!$D$36) | D97: =IF('単価表'!$E$36="","",'単価表'!$E$36)
A98: =IF('単価表'!$A$37="","",'単価表'!$A$37) | B98: 昼 | C98: =IF('単価表'!$B$37="","",'単価表'!$B$37) | D98: =IF('単価表'!$E$37="","",'単価表'!$E$37)
A99: =IF('単価表'!$A$37="","",'単価表'!$A$37) | B99: 夜 | C99: =IF('単価表'!$C$37="","",'単価表'!$C$37) | D99: =IF('単価表'!$E$37="","",'単価表'!$E$37)
A100: =IF('単価表'!$A$37="","",'単価表'!$A$37) | B100: その他 | C100: =IF('単価表'!$D$37="","",'単価表'!$D$37) | D100: =IF('単価表'!$E$37="","",'単価表'!$E$37)
...

Sheet 旧配車表
A1: 旧配車表(過去データ保管用・非表示シート)
A2: 旧システムからの過去データを移行する場合はこのシートに貼り付けてください。

Sheet 裏集計
A1: 区分リスト | B1: 傭車区分リスト | C1: チェックリスト | E1: 各シートのドロップダウンの選択肢を管理しています。行の追加・削除はしないでください。
A2: 昼 | B2: 自社 | C2: 済
A3: 夜 | B3: 傭車 | C3: 未
A4: その他
